nigeria_banks/__init__.py
nigeria_banks/__version__.py
nigeria_banks/bank.py
nigeria_banks/database/__init__.py
nigeria_banks/database/db.py
nigeria_banks-0.1.8.dist-info/licenses/LICENSE
nigeria_banks-0.1.8.dist-info/METADATA
nigeria_banks-0.1.8.dist-info/WHEEL
nigeria_banks-0.1.8.dist-info/top_level.txt
nigeria_banks-0.1.8.dist-info/RECORD
